ais_wordnet_sim/__init__.py
ais_wordnet_sim/aiml_enrich/__init__.py
ais_wordnet_sim/aiml_enrich/enrich_model.py
ais_wordnet_sim/database/__init__.py
ais_wordnet_sim/database/config.py
ais_wordnet_sim/database/model.py
ais_wordnet_sim/database/service.py
ais_wordnet_sim/similar_sentences/__init__.py
ais_wordnet_sim/similar_sentences/sim_sentence_model.py
ais_wordnet_sim/utility/__init__.py
ais_wordnet_sim/utility/preprocessing.py
ais_wordnet_sim-2.0.0.dist-info/LICENSE.txt
ais_wordnet_sim-2.0.0.dist-info/METADATA
ais_wordnet_sim-2.0.0.dist-info/WHEEL
ais_wordnet_sim-2.0.0.dist-info/top_level.txt
ais_wordnet_sim-2.0.0.dist-info/RECORD
