Metadata-Version: 2.1
Name: ais-wordnet-sim
Version: 2.0.0
Summary: AIS Wordnet tool
Home-page: https://https://github.com/liv1n9/ais-wordnet-sim
Author: Tan Nguyen
Author-email: livw08@gmail.com
License: UNKNOWN
Platform: UNKNOWN
Classifier: Programming Language :: Python :: 3
Classifier: Operating System :: OS Independent
Classifier: License :: OSI Approved :: MIT License
Requires-Dist: underthesea
Requires-Dist: pymongo
Requires-Dist: dnspython
Requires-Dist: xlrd
